<?xml version="1.0" encoding="UTF-8"?>

		<srv:SV_OperationMetadata>
			<srv:operationName>
				<gco:CharacterString>GetRequestStatus</gco:CharacterString>
			</srv:operationName>
			<srv:DCP>
				<srv:DCPList codeList="" codeListValue=""/>
			</srv:DCP>			
			<srv:operationDescription>
				<gco:CharacterString>Process to check the status of a request. 	  
	The purpose of this process is to to check the status of a request (pending, in progress, done, error) from a request identifier.
	The request identifier is provided by the result of an extraction process.
	The return values are the status of the request (pending, in progress, done, error), 
	the request identifer and the return process code (ok or error code) and the correponding message)				</gco:CharacterString>
			</srv:operationDescription>
			<srv:invocationName>
				<gco:CharacterString>GetRequestStatus</gco:CharacterString>
			</srv:invocationName>
		&requestIdInputParameters;
		&statusResponseOutputParameters;
		&commonBasicOutputParameters;
																				
			<srv:connectPoint>
				<gmd:CI_OnlineResource>
					<gmd:linkage>
						<gmd:URL><![CDATA[${connectPoint}]]></gmd:URL>
					</gmd:linkage>
				</gmd:CI_OnlineResource>
			</srv:connectPoint>
			
		</srv:SV_OperationMetadata>
